fds/__init__.py
fds/sdk/__init__.py
fds/sdk/Formula/__init__.py
fds/sdk/Formula/api_client.py
fds/sdk/Formula/configuration.py
fds/sdk/Formula/exceptions.py
fds/sdk/Formula/model_utils.py
fds/sdk/Formula/rest.py
fds/sdk/Formula/api/__init__.py
fds/sdk/Formula/api/batch_processing_api.py
fds/sdk/Formula/api/cross_sectional_api.py
fds/sdk/Formula/api/time_series_api.py
fds/sdk/Formula/apis/__init__.py
fds/sdk/Formula/model/__init__.py
fds/sdk/Formula/model/batch_data.py
fds/sdk/Formula/model/batch_data_request.py
fds/sdk/Formula/model/batch_data_request_data.py
fds/sdk/Formula/model/batch_data_response.py
fds/sdk/Formula/model/batch_list.py
fds/sdk/Formula/model/batch_list_response.py
fds/sdk/Formula/model/batch_list_response_meta.py
fds/sdk/Formula/model/batch_status.py
fds/sdk/Formula/model/batch_status_response.py
fds/sdk/Formula/model/cross_sectional_request.py
fds/sdk/Formula/model/cross_sectional_request_data.py
fds/sdk/Formula/model/cross_sectional_response.py
fds/sdk/Formula/model/cross_sectional_response_object_items.py
fds/sdk/Formula/model/cross_sectional_result_object_nonflattened.py
fds/sdk/Formula/model/cross_sectional_result_object_nonflattened_result_attribute.py
fds/sdk/Formula/model/error_detail.py
fds/sdk/Formula/model/error_object.py
fds/sdk/Formula/model/time_series_request.py
fds/sdk/Formula/model/time_series_request_data.py
fds/sdk/Formula/model/time_series_response.py
fds/sdk/Formula/model/time_series_response_object_items.py
fds/sdk/Formula/model/time_series_result_object_nonflattened.py
fds/sdk/Formula/model/time_series_result_object_nonflattened_array.py
fds/sdk/Formula/model/time_series_result_object_nonflattened_base.py
fds/sdk/Formula/model/time_series_result_object_nonflattened_matrix.py
fds/sdk/Formula/model/time_series_result_object_nonflattened_scalar.py
fds/sdk/Formula/model/time_series_result_object_nonflattened_timeseries_object.py
fds/sdk/Formula/model/time_series_scalar_value.py
fds_sdk_formula-4.0.0.dist-info/licenses/LICENSE
fds_sdk_formula-4.0.0.dist-info/METADATA
fds_sdk_formula-4.0.0.dist-info/WHEEL
fds_sdk_formula-4.0.0.dist-info/top_level.txt
fds_sdk_formula-4.0.0.dist-info/RECORD
